lesson1/__init__.py
python_2025_lesson1-0.1.0.dist-info/METADATA
python_2025_lesson1-0.1.0.dist-info/WHEEL
python_2025_lesson1-0.1.0.dist-info/RECORD
